uhid/__init__.py
uhid-0.0.1.dist-info/LICENSE
uhid-0.0.1.dist-info/METADATA
uhid-0.0.1.dist-info/WHEEL
uhid-0.0.1.dist-info/top_level.txt
uhid-0.0.1.dist-info/RECORD
